LICENSE
MANIFEST.in
README.md
setup.py
cfy_cluster_manager/__init__.py
cfy_cluster_manager/logger.py
cfy_cluster_manager/main.py
cfy_cluster_manager/utils.py
cfy_cluster_manager/cfy_cluster_config_files/cfy_nine_nodes_cluster_config.yaml
cfy_cluster_manager/cfy_cluster_config_files/cfy_nine_nodes_external_db_cluster_config.yaml
cfy_cluster_manager/cfy_cluster_config_files/cfy_three_nodes_cluster_config.yaml
cfy_cluster_manager/cfy_cluster_config_files/cfy_three_nodes_external_db_cluster_config.yaml
cfy_cluster_manager/config_files_templates/manager_config.yaml
cfy_cluster_manager/config_files_templates/postgresql_config.yaml
cfy_cluster_manager/config_files_templates/rabbitmq_config.yaml
cfy_cluster_manager/scripts/create_installation_files.py
cloudify_cluster_manager.egg-info/PKG-INFO
cloudify_cluster_manager.egg-info/SOURCES.txt
cloudify_cluster_manager.egg-info/dependency_links.txt
cloudify_cluster_manager.egg-info/entry_points.txt
cloudify_cluster_manager.egg-info/requires.txt
cloudify_cluster_manager.egg-info/top_level.txt