Metadata-Version: 2.1
Name: cloudify-cluster-manager
Version: 1.1.5
Summary: Install a Cloudify cluster
Author: Cloudify
Author-email: cosmo-admin@cloudify.co
License: LICENSE
License-File: LICENSE
